pyansiescapes/__init__.py
pyansiescapes/_types.py
pyansiescapes/commands.py
pyansiescapes/enums.py
pyansiescapes/utils.py
pyansiescapes-0.0.1.dev61.dist-info/LICENSE
pyansiescapes-0.0.1.dev61.dist-info/METADATA
pyansiescapes-0.0.1.dev61.dist-info/WHEEL
pyansiescapes-0.0.1.dev61.dist-info/top_level.txt
pyansiescapes-0.0.1.dev61.dist-info/RECORD
