Metadata-Version: 2.1
Name: pyansiescapes
Version: 0.0.1.dev61
Summary: Python package for quick and readable console manipulation using ANSI Escapes Sequences
Home-page: https://github.com/tillhainbach/pyansiescapes
Author: Till Hainbach
Author-email: Till.Hainbach@posteo.de
License: UNKNOWN
Project-URL: Bug Reports, https://github.com/tillhainbach/pyansiescapes/issues
Project-URL: Documentation, https://pyansiescapes.readthedocs.io/en/latest/
Project-URL: Source, https://github.com/tillhainbach/pyansiescapes
Platform: UNKNOWN
Classifier: Development Status :: 2 - Pre-Alpha
Classifier: License :: OSI Approved :: MIT License
Classifier: Programming Language :: Python :: 3 
Classifier: Programming Language :: Python :: 3 :: Only
Requires-Python: >=3.5
Requires-Dist: emojis
